mudanca.cpython-310-darwin.so
mudanca-1.5.0.dist-info/LICENSE
mudanca-1.5.0.dist-info/METADATA
mudanca-1.5.0.dist-info/WHEEL
mudanca-1.5.0.dist-info/top_level.txt
mudanca-1.5.0.dist-info/RECORD
