Metadata-Version: 2.1
Name: mudanca
Version: 1.5.0
Summary: An implementation of the shift algorithmn for python ported from Darktable & Nshift
Author: James Campbell
License-File: LICENSE
